.travis.yml
MANIFEST.in
README.md
VERSION
requirements.txt
setup.py
newslynx_sc_example/__init__.py
newslynx_sc_example.egg-info/PKG-INFO
newslynx_sc_example.egg-info/SOURCES.txt
newslynx_sc_example.egg-info/dependency_links.txt
newslynx_sc_example.egg-info/namespace_packages.txt
newslynx_sc_example.egg-info/not-zip-safe
newslynx_sc_example.egg-info/requires.txt
newslynx_sc_example.egg-info/top_level.txt