Metadata-Version: 1.1
Name: newslynx-sc-example
Version: 0.0.1
Summary: An example Sous Chef module generated by 
Home-page: http://github.com/newslynx/newslynx-sc-example
Author: Merlynne
Author-email: UNKNOWN
License: MIT
Platform: UNKNOWN
Classifier: Development Status :: 3 - Alpha
Classifier: Intended Audience :: Developers
Classifier: License :: OSI Approved :: MIT License
Classifier: Operating System :: OS Independent
Classifier: Programming Language :: Python
